protopypes/.gitattributes
protopypes/__init__.py
protopypes/base/__init__.py
protopypes/base/config.py
protopypes/base/pypeline.py
protopypes/base/step.py
protopypes/models.py
protopypes/pypeline.py
protopypes/step.py
protopypes/tools/__init__.py
protopypes/tools/retry.py
protopypes/tools/timer.py
protopypes-0.1.0.dist-info/LICENSE
protopypes-0.1.0.dist-info/WHEEL
protopypes-0.1.0.dist-info/METADATA
protopypes-0.1.0.dist-info/RECORD
